<?xml version="1.0" encoding="utf-8" ?>
<dwsync>
<file name="IMG_5919.jpg" server="ftp.allogin.net/grande.lv/" local="129562892360046415" remote="129562795200000000" />
<file name="IMG_5937.jpg" server="ftp.allogin.net/grande.lv/" local="129562892284882116" remote="129562795200000000" />
<file name="IMG_5943.jpg" server="ftp.allogin.net/grande.lv/" local="129562892246389914" remote="129562795200000000" />
<file name="IMG_5948.jpg" server="ftp.allogin.net/grande.lv/" local="129562892209667814" remote="129562795200000000" />
<file name="IMG_5977.jpg" server="ftp.allogin.net/grande.lv/" local="129562892187826565" remote="129562795200000000" />
<file name="IMG_5999.jpg" server="ftp.allogin.net/grande.lv/" local="129562892071819929" remote="129562795200000000" />
<file name="IMG_6002.jpg" server="ftp.allogin.net/grande.lv/" local="129562892143744043" remote="129562795200000000" />
<file name="IMG_6005.jpg" server="ftp.allogin.net/grande.lv/" local="129562891953733175" remote="129562795200000000" />
</dwsync>